dizest_MCP/__init__.py
dizest_MCP/__main__.py
dizest_MCP/cli.py
dizest_MCP/mcp_server.py
dizest_MCP/tools/__init__.py
dizest_MCP/tools/analyze_existing_file.py
dizest_MCP/tools/analyze_parallelization.py
dizest_MCP/tools/create_flow.py
dizest_MCP/tools/python_repl_tool.py
dizest_MCP/tools/tavily_search.py
dizest_mcp-0.1.2.dist-info/METADATA
dizest_mcp-0.1.2.dist-info/WHEEL
dizest_mcp-0.1.2.dist-info/entry_points.txt
dizest_mcp-0.1.2.dist-info/top_level.txt
dizest_mcp-0.1.2.dist-info/RECORD
